pycanon/__init__.py
pycanon/anonymity/__init__.py
pycanon/anonymity/_beta_likeness.py
pycanon/anonymity/_delta_disclosure.py
pycanon/anonymity/_k_anonymity.py
pycanon/anonymity/_l_diversity.py
pycanon/anonymity/_t_closeness.py
pycanon/anonymity/utils/__init__.py
pycanon/anonymity/utils/aux_anonymity.py
pycanon/anonymity/utils/aux_functions.py
pycanon/cli.py
pycanon/report/__init__.py
pycanon/report/base.py
pycanon/report/json.py
pycanon/report/pdf.py
pycanon/report/pdf_utility_report.py
pycanon/utility/__init__.py
pycanon/utility/_attribute_statistics.py
pycanon/utility/_reidentification_metrics.py
pycanon/utility/_utility_metrics.py
pycanon-1.1.0.dist-info/METADATA
pycanon-1.1.0.dist-info/WHEEL
pycanon-1.1.0.dist-info/licenses/LICENSE
pycanon-1.1.0.dist-info/RECORD
