Metadata-Version: 2.4
Name: pycanon
Version: 1.1.0
Summary: pyCANON: A Python library to check the level of anonymity of a dataset.
License: Apache-2.0
License-File: LICENSE
Keywords: data,privacy,anonymity
Author: Judith Sáinz-Pardo Díaz
Author-email: sainzpardo@ifca.unican.es
Maintainer: Judith Sáinz-Pardo Díaz
Maintainer-email: sainzpardo@ifca.unican.es
Requires-Python: >=3.9,<4.0
Classifier: Development Status :: 5 - Production/Stable
Classifier: Intended Audience :: Developers
Classifier: Intended Audience :: Education
Classifier: Intended Audience :: Science/Research
Classifier: License :: OSI Approved :: Apache Software License
Classifier: Programming Language :: Python :: 3
Classifier: Programming Language :: Python :: 3.9
Classifier: Programming Language :: Python :: 3.10
Classifier: Programming Language :: Python :: 3.11
Classifier: Programming Language :: Python :: 3.12
Classifier: Programming Language :: Python :: 3.13
Classifier: Programming Language :: Python :: 3.14
Classifier: Programming Language :: Python :: 3 :: Only
Classifier: Programming Language :: Python :: 3.8
Classifier: Topic :: Scientific/Engineering
Classifier: Topic :: Scientific/Engineering :: Mathematics
Classifier: Topic :: Security
Requires-Dist: beartype (==0.21.0)
Requires-Dist: docutils (==0.22.1)
Requires-Dist: numpy (==2.0.2)
Requires-Dist: pandas (==2.3.0)
Requires-Dist: reportlab (==4.4.4)
Requires-Dist: tabulate (==0.8.10)
Requires-Dist: typer (==0.17.4)
Requires-Dist: typing_extensions (==4.15.0)
Project-URL: Repository, https://github.com/IFCA-Advanced-Computing/pycanon
